firefly_sbom/__init__.py
firefly_sbom/cli.py
firefly_sbom/config.py
firefly_sbom/core.py
firefly_sbom/auditors/__init__.py
firefly_sbom/generators/__init__.py
firefly_sbom/scanners/__init__.py
firefly_sbom/scanners/base.py
firefly_sbom/scanners/flutter.py
firefly_sbom/scanners/go.py
firefly_sbom/scanners/maven.py
firefly_sbom/scanners/node.py
firefly_sbom/scanners/python.py
firefly_sbom/scanners/ruby.py
firefly_sbom/scanners/rust.py
firefly_sbom/utils/__init__.py
firefly_sbom/utils/github.py
firefly_sbom/utils/logger.py
firefly_sbom/utils/parallel.py
firefly_sbom_tool-1.0.0.dist-info/licenses/LICENSE
firefly_sbom_tool-1.0.0.dist-info/METADATA
firefly_sbom_tool-1.0.0.dist-info/WHEEL
firefly_sbom_tool-1.0.0.dist-info/entry_points.txt
firefly_sbom_tool-1.0.0.dist-info/top_level.txt
firefly_sbom_tool-1.0.0.dist-info/RECORD
