Metadata-Version: 2.4
Name: firefly-sbom-tool
Version: 1.0.0
Summary: Comprehensive SBOM generation and auditing tool for Firefly Open Banking Platform
Home-page: https://github.com/firefly-oss/sbom-tool
Author: Firefly OSS
Author-email: oss@firefly.com
Classifier: Development Status :: 4 - Beta
Classifier: Intended Audience :: Developers
Classifier: License :: OSI Approved :: Apache Software License
Classifier: Operating System :: OS Independent
Classifier: Programming Language :: Python :: 3
Classifier: Programming Language :: Python :: 3.8
Classifier: Programming Language :: Python :: 3.9
Classifier: Programming Language :: Python :: 3.10
Classifier: Programming Language :: Python :: 3.11
Classifier: Topic :: Software Development :: Libraries :: Python Modules
Classifier: Topic :: Security
Classifier: Topic :: System :: Software Distribution
Requires-Python: >=3.8
License-File: LICENSE
Requires-Dist: click>=8.0
Requires-Dist: PyYAML>=6.0
Requires-Dist: requests>=2.31
Requires-Dist: rich>=13.0
Requires-Dist: Jinja2>=3.1
Requires-Dist: cyclonedx-python-lib>=6.4
Requires-Dist: spdx-tools>=0.8
Requires-Dist: packageurl-python>=0.11
Requires-Dist: pip-audit>=2.7
Requires-Dist: pandas>=2.0
Requires-Dist: tabulate>=0.9
Requires-Dist: GitPython>=3.1
Dynamic: author
Dynamic: author-email
Dynamic: classifier
Dynamic: description
Dynamic: description-content-type
Dynamic: home-page
Dynamic: license-file
Dynamic: requires-dist
Dynamic: requires-python
Dynamic: summary
